[
  {
    "id": 1,
    "category": "cornice",
    "title": "Карниз стельовий C1",
    "price": 210,
    "img": "../../data/dataImg/cornice1.webp",
    "brand": "NMC",
    "desc": "Класичний карниз для високих стель."
  },
  {
    "id": 2,
    "category": "molding",
    "title": "Молдинг стіновий M5",
    "price": 150,
    "img": "../../data/dataImg/cornice1.webp",
    "brand": "ORAC",
    "desc": "Тонкий молдинг для зонування стін."
  },
  {
    "id": 3,
    "category": "cornice",
    "title": "Карниз стельовий C2",
    "price": 170,
    "img": "../../data/dataImg/cornice1.webp",
    "brand": "None",
    "desc": "Класичний карниз для високих стель."
  },
  {
    "id": 4,
    "category": "cornice",
    "title": "Карниз стельовий C2",
    "price": 170,
    "img": "../../data/dataImg/cornice1.webp",
    "newArrivals": true,
    "brand": "None",
    "desc": "Класичний карниз для високих стель."
  },
  {
    "id": 5,
    "category": "cornice",
    "title": "Карниз стельовий C22",
    "price": 170,
    "img": "../../data/dataImg/cornice1.webp",
    "newArrivals": true,
    "brand": "None",
    "desc": "Класичний карниз для високих стель."
  },
  {
    "id": 6,
    "category": "skirting",
    "title": "Плінтус стельовий C22",
    "price": 370,
    "img": "../../data/dataImg/cornice1.webp",
    "brand": "None",
    "desc": "Класичний карниз для високих стель."
  },
  {
    "id": 7,
    "category": "wallpanel",
    "title": "Панель стінова стельовий C22",
    "price": 370,
    "img": "../../data/dataImg/cornice1.webp",
    "brand": "None",
    "desc": "Класичний карниз для високих стель."
  },
  {
    "id": 8,
    "category": "light",
    "title": "Світильник A1",
    "price": 350,
    "img": "../../data/dataImg/cornice1.webp",
    "brand": "NMC",
    "desc": "Класичний карниз для високих стель."
  },
  {
    "id": 9,
    "category": "scenery",
    "title": "Декоративна панель A105",
    "price": 380,
    "img": "../../data/dataImg/cornice1.webp",
    "brand": "ORAC",
    "desc": "Класичний карниз для високих стель."
  },
  {
    "id": 10,
    "category": "tool",
    "title": "Клей CT117",
    "price": 380,
    "img": "../../data/dataImg/cornice1.webp",
    "brand": "None",
    "desc": "Класичний карниз для високих стель."
  }
]
